Metadata-Version: 2.1
Name: situla
Version: 0.1
Summary: Create bins for features as part of a modeling pipeline.
Home-page: https://github.com/andyreagan/situla
Author: Andy Reagan
Author-email: andy@andyreagan.com
License: MIT
Project-URL: Issue Tracker, https://github.com/andyreagan/situla/issues
Platform: UNKNOWN
Classifier: Development Status :: 5 - Production/Stable
Classifier: Intended Audience :: Developers
Classifier: License :: OSI Approved :: MIT License
Classifier: Operating System :: Unix
Classifier: Operating System :: POSIX
Classifier: Programming Language :: Python
Classifier: Programming Language :: Python :: 3
Classifier: Programming Language :: Python :: 3.6
Classifier: Programming Language :: Python :: 3.7
Classifier: Topic :: Utilities
Requires-Python: >=3.6
